swellow/.gitignore
swellow/__init__.py
swellow/app.py
swellow/cli.py
swellow/bin/swellow-linux-x86_64/swellow
swellow/bin/swellow-macos-aarch64/swellow
swellow/bin/swellow-windows-x86_64/swellow.exe
swellow-0.1.2.dist-info/METADATA
swellow-0.1.2.dist-info/WHEEL
swellow-0.1.2.dist-info/entry_points.txt
swellow-0.1.2.dist-info/licenses/LICENSE
swellow-0.1.2.dist-info/RECORD
