Metadata-Version: 2.4
Name: swellow
Version: 0.1.2
Summary: SQL-first table migrations.
Author-email: "Francisco A. B. Sampaio" <franciscoabsampaio@gmail.com>
License-Expression: MIT
License-File: LICENSE
Classifier: Programming Language :: Python
Classifier: Programming Language :: Python :: Implementation :: CPython
Classifier: Programming Language :: Rust
Requires-Python: >=3.9
Provides-Extra: test
Requires-Dist: pytest>=8.4.2; extra == 'test'
Requires-Dist: testcontainers>=4.13.0; extra == 'test'
